<MD_Metadata xmlns="http://www.isotc211.org/2005/gmd" xmlns:gco="http://www.isotc211.org/2005/gco" xmlns:gts="http://www.isotc211.org/2005/gts" xmlns:srv="http://www.isotc211.org/2005/srv" xmlns:gml="http://www.opengis.net/gml" xmlns:xlink="http://www.w3.org/1999/xlink" xmlns:xsi="http://www.w3.org/2001/XMLSchema-instance">
  <fileIdentifier>
    <gco:CharacterString>28722/bk0016d1x3d</gco:CharacterString>
  </fileIdentifier>
  <language>
    <LanguageCode codeList="http://www.loc.gov/standards/iso639-2/php/code_list.php" codeListValue="eng" codeSpace="ISO639-2">eng</LanguageCode>
  </language>
  <characterSet>
    <MD_CharacterSetCode codeList="http://www.isotc211.org/2005/resources/Codelist/gmxCodelists.xml#MD_CharacterSetCode" codeListValue="utf8" codeSpace="ISOTC211/19115">utf8</MD_CharacterSetCode>
  </characterSet>
  <hierarchyLevel>
    <MD_ScopeCode codeList="http://www.isotc211.org/2005/resources/Codelist/gmxCodelists.xml#MD_ScopeCode" codeListValue="dataset" codeSpace="ISOTC211/19115">dataset</MD_ScopeCode>
  </hierarchyLevel>
  <hierarchyLevelName>
    <gco:CharacterString>dataset</gco:CharacterString>
  </hierarchyLevelName>
  <contact>
    <CI_ResponsibleParty>
      <individualName>
        <gco:CharacterString>Fred Vogler</gco:CharacterString>
      </individualName>
      <organisationName>
        <gco:CharacterString>County of Marin Community Development Agency</gco:CharacterString>
      </organisationName>
      <positionName>
        <gco:CharacterString>GIS Manager</gco:CharacterString>
      </positionName>
      <contactInfo>
        <CI_Contact>
          <phone>
            <CI_Telephone>
              <voice>
                <gco:CharacterString>415-499-6286</gco:CharacterString>
              </voice>
            </CI_Telephone>
          </phone>
          <address>
            <CI_Address>
              <deliveryPoint>
                <gco:CharacterString>65 Mitchell Blvd, Suite 100G</gco:CharacterString>
              </deliveryPoint>
              <city>
                <gco:CharacterString>San Rafael</gco:CharacterString>
              </city>
              <administrativeArea>
                <gco:CharacterString>CA</gco:CharacterString>
              </administrativeArea>
              <postalCode>
                <gco:CharacterString>94903</gco:CharacterString>
              </postalCode>
              <country>
                <Country codeList="http://www.iso.org/iso/country_codes/iso_3166_code_lists.htm" codeListValue="US" codeSpace="ISO3166-1">US</Country>
              </country>
              <electronicMailAddress>
                <gco:CharacterString>fvogler@co.marin.ca.us</gco:CharacterString>
              </electronicMailAddress>
            </CI_Address>
          </address>
        </CI_Contact>
      </contactInfo>
      <role>
        <CI_RoleCode codeList="http://www.isotc211.org/2005/resources/Codelist/gmxCodelists.xml#CI_RoleCode" codeListValue="pointOfContact" codeSpace="ISOTC211/19115">pointOfContact</CI_RoleCode>
      </role>
    </CI_ResponsibleParty>
  </contact>
  <contact>
    <CI_ResponsibleParty>
      <organisationName>
        <gco:CharacterString>UC Berkeley Library </gco:CharacterString>
      </organisationName>
      <positionName>
        <gco:CharacterString>GIS Librarian </gco:CharacterString>
      </positionName>
      <contactInfo>
        <CI_Contact>
          <phone>
            <CI_Telephone>
              <voice>
                <gco:CharacterString>(510) 642-2997</gco:CharacterString>
              </voice>
            </CI_Telephone>
          </phone>
          <address>
            <CI_Address>
              <deliveryPoint>
                <gco:CharacterString>50 McCone Hall</gco:CharacterString>
              </deliveryPoint>
              <city>
                <gco:CharacterString>Berkeley</gco:CharacterString>
              </city>
              <administrativeArea>
                <gco:CharacterString>CA</gco:CharacterString>
              </administrativeArea>
              <postalCode>
                <gco:CharacterString>94720</gco:CharacterString>
              </postalCode>
              <country>
                <Country codeList="http://www.iso.org/iso/country_codes/iso_3166_code_lists.htm" codeListValue="US" codeSpace="ISO3166-1">US</Country>
              </country>
              <electronicMailAddress>
                <gco:CharacterString>eart@library.berkeley.edu</gco:CharacterString>
              </electronicMailAddress>
            </CI_Address>
          </address>
        </CI_Contact>
      </contactInfo>
      <role>
        <CI_RoleCode codeList="http://www.isotc211.org/2005/resources/Codelist/gmxCodelists.xml#CI_RoleCode" codeListValue="pointOfContact" codeSpace="ISOTC211/19115">pointOfContact</CI_RoleCode>
      </role>
    </CI_ResponsibleParty>
  </contact>
  <dateStamp>
    <gco:Date>2017-12-19</gco:Date>
  </dateStamp>
  <metadataStandardName>
    <gco:CharacterString>ISO 19139 Geographic Information - Metadata - Implementation Specification</gco:CharacterString>
  </metadataStandardName>
  <metadataStandardVersion>
    <gco:CharacterString>2007</gco:CharacterString>
  </metadataStandardVersion>
  <dataSetURI>
    <gco:CharacterString>28722/bk0016d1x3d</gco:CharacterString>
  </dataSetURI>
  <spatialRepresentationInfo>
    <MD_VectorSpatialRepresentation>
      <topologyLevel>
        <MD_TopologyLevelCode codeList="http://www.isotc211.org/2005/resources/Codelist/gmxCodelists.xml#MD_TopologyLevelCode" codeListValue="geometryOnly" codeSpace="ISOTC211/19115">geometryOnly</MD_TopologyLevelCode>
      </topologyLevel>
      <geometricObjects>
        <MD_GeometricObjects>
          <geometricObjectType>
            <MD_GeometricObjectTypeCode codeList="http://www.isotc211.org/2005/resources/Codelist/gmxCodelists.xml#MD_GeometricObjectTypeCode" codeListValue="composite" codeSpace="ISOTC211/19115">composite</MD_GeometricObjectTypeCode>
          </geometricObjectType>
          <geometricObjectCount>
            <gco:Integer>1456</gco:Integer>
          </geometricObjectCount>
        </MD_GeometricObjects>
      </geometricObjects>
    </MD_VectorSpatialRepresentation>
  </spatialRepresentationInfo>
  <referenceSystemInfo>
    <MD_ReferenceSystem>
      <referenceSystemIdentifier>
        <RS_Identifier>
          <code>
            <gco:CharacterString>2872</gco:CharacterString>
          </code>
          <codeSpace>
            <gco:CharacterString>EPSG</gco:CharacterString>
          </codeSpace>
          <version>
            <gco:CharacterString>8.9.3(9.0.0)</gco:CharacterString>
          </version>
        </RS_Identifier>
      </referenceSystemIdentifier>
    </MD_ReferenceSystem>
  </referenceSystemInfo>
  <identificationInfo>
    <MD_DataIdentification>
      <citation>
        <CI_Citation>
          <title>
            <gco:CharacterString>Bikeways, Marin County, California, 2014</gco:CharacterString>
          </title>
          <date>
            <CI_Date>
              <date>
                <gco:Date>2007-11-06</gco:Date>
              </date>
              <dateType>
                <CI_DateTypeCode codeList="http://www.isotc211.org/2005/resources/Codelist/gmxCodelists.xml#CI_DateTypeCode" codeListValue="publication" codeSpace="ISOTC211/19115">publication</CI_DateTypeCode>
              </dateType>
            </CI_Date>
          </date>
          <citedResponsibleParty>
            <CI_ResponsibleParty>
              <organisationName>
                <gco:CharacterString>Marin County Community Development Agency</gco:CharacterString>
              </organisationName>
              <role>
                <CI_RoleCode codeList="http://www.isotc211.org/2005/resources/Codelist/gmxCodelists.xml#CI_RoleCode" codeListValue="originator" codeSpace="ISOTC211/19115">originator</CI_RoleCode>
              </role>
            </CI_ResponsibleParty>
          </citedResponsibleParty>
          <citedResponsibleParty>
            <CI_ResponsibleParty>
              <organisationName>
                <gco:CharacterString>County of Marin</gco:CharacterString>
              </organisationName>
              <contactInfo>
                <CI_Contact>
                  <address>
                    <CI_Address>
                      <deliveryPoint>
                        <gco:CharacterString>San Rafael</gco:CharacterString>
                      </deliveryPoint>
                    </CI_Address>
                  </address>
                </CI_Contact>
              </contactInfo>
              <role>
                <CI_RoleCode codeList="http://www.isotc211.org/2005/resources/Codelist/gmxCodelists.xml#CI_RoleCode" codeListValue="publisher" codeSpace="ISOTC211/19115">publisher</CI_RoleCode>
              </role>
            </CI_ResponsibleParty>
          </citedResponsibleParty>
          <presentationForm>
            <CI_PresentationFormCode codeList="http://www.isotc211.org/2005/resources/Codelist/gmxCodelists.xml#CI_PresentationFormCode" codeListValue="mapDigital" codeSpace="ISOTC211/19115">mapDigital</CI_PresentationFormCode>
          </presentationForm>
          <series>
            <CI_Series>
              <name>
                <gco:CharacterString>Marin Countywide Plan</gco:CharacterString>
              </name>
            </CI_Series>
          </series>
        </CI_Citation>
      </citation>
      <abstract>
        <gco:CharacterString>Bikeways were defined by the "Marin County Bicycle and Pedestrian Master Plan" (January 2000) and "Marin County Unincorporated Area Bicycle and Pedestrian Master Plan" (June 2001) by Alta Transportation Consulting. Data was both digitized and extracted from existing road data. Attribute BIKECLASS is defined as: 1 = Existing Bike Paths (Class 1) 2 = Existing Bike Lanes/Shoulders (Class 2) 3 = Existing Bike Routes (Class 3) Attribute BIKEPROP is defined as: 1 = Proposed Bike Paths (Class 1) 2 = Proposed Bike Lanes/Shoulders (Class 2) 3 = Proposed Bike Routes (Class 3)</gco:CharacterString>
      </abstract>
      <purpose>
        <gco:CharacterString>To provide Bikeways data for the Marin Countywide Plan Update.</gco:CharacterString>
      </purpose>
      <credit>
        <gco:CharacterString>Marin County Community Development Agency (2014) Bikeways, Marin County, California. Marin County Assessor's Office, Marin Local Agency Formation Commission, Marin County, California. 



</gco:CharacterString>
      </credit>
      <status>
        <MD_ProgressCode codeList="http://www.isotc211.org/2005/resources/Codelist/gmxCodelists.xml#MD_ProgressCode" codeListValue="onGoing" codeSpace="ISOTC211/19115">onGoing</MD_ProgressCode>
      </status>
      <pointOfContact>
        <CI_ResponsibleParty>
          <individualName>
            <gco:CharacterString>Kristin Drumm</gco:CharacterString>
          </individualName>
          <organisationName>
            <gco:CharacterString>Marin County Community Development Agency</gco:CharacterString>
          </organisationName>
          <positionName>
            <gco:CharacterString>Senior Planner</gco:CharacterString>
          </positionName>
          <contactInfo>
            <CI_Contact>
              <phone>
                <CI_Telephone>
                  <voice>
                    <gco:CharacterString>415-499-6290</gco:CharacterString>
                  </voice>
                  <facsimile>
                    <gco:CharacterString>415-499-7880</gco:CharacterString>
                  </facsimile>
                </CI_Telephone>
              </phone>
              <address>
                <CI_Address>
                  <electronicMailAddress>
                    <gco:CharacterString>kdrumm@co.marin.ca.us</gco:CharacterString>
                  </electronicMailAddress>
                </CI_Address>
              </address>
            </CI_Contact>
          </contactInfo>
          <role>
            <CI_RoleCode codeList="http://www.isotc211.org/2005/resources/Codelist/gmxCodelists.xml#CI_RoleCode" codeListValue="pointOfContact" codeSpace="ISOTC211/19115">pointOfContact</CI_RoleCode>
          </role>
        </CI_ResponsibleParty>
      </pointOfContact>
      <pointOfContact>
        <CI_ResponsibleParty>
          <organisationName>
            <gco:CharacterString>UC Berkeley Library </gco:CharacterString>
          </organisationName>
          <positionName>
            <gco:CharacterString>GIS Librarian </gco:CharacterString>
          </positionName>
          <contactInfo>
            <CI_Contact>
              <phone>
                <CI_Telephone>
                  <voice>
                    <gco:CharacterString>(510) 642-2997</gco:CharacterString>
                  </voice>
                </CI_Telephone>
              </phone>
              <address>
                <CI_Address>
                  <deliveryPoint>
                    <gco:CharacterString>50 McCone Hall</gco:CharacterString>
                  </deliveryPoint>
                  <city>
                    <gco:CharacterString>Berkeley</gco:CharacterString>
                  </city>
                  <administrativeArea>
                    <gco:CharacterString>CA</gco:CharacterString>
                  </administrativeArea>
                  <postalCode>
                    <gco:CharacterString>94720</gco:CharacterString>
                  </postalCode>
                  <country>
                    <Country codeList="http://www.iso.org/iso/country_codes/iso_3166_code_lists.htm" codeListValue="US" codeSpace="ISO3166-1">US</Country>
                  </country>
                  <electronicMailAddress>
                    <gco:CharacterString>eart@library.berkeley.edu</gco:CharacterString>
                  </electronicMailAddress>
                </CI_Address>
              </address>
            </CI_Contact>
          </contactInfo>
          <role>
            <CI_RoleCode codeList="http://www.isotc211.org/2005/resources/Codelist/gmxCodelists.xml#CI_RoleCode" codeListValue="pointOfContact" codeSpace="ISOTC211/19115">pointOfContact</CI_RoleCode>
          </role>
        </CI_ResponsibleParty>
      </pointOfContact>
      <resourceMaintenance>
        <MD_MaintenanceInformation>
          <maintenanceAndUpdateFrequency>
            <MD_MaintenanceFrequencyCode codeList="http://www.isotc211.org/2005/resources/Codelist/gmxCodelists.xml#MD_MaintenanceFrequencyCode" codeListValue="notPlanned" codeSpace="ISOTC211/19115">notPlanned</MD_MaintenanceFrequencyCode>
          </maintenanceAndUpdateFrequency>
        </MD_MaintenanceInformation>
      </resourceMaintenance>
      <descriptiveKeywords>
        <MD_Keywords>
          <keyword>
            <gco:CharacterString>Marin County (Calif.)</gco:CharacterString>
          </keyword>
          <type>
            <MD_KeywordTypeCode codeList="http://www.isotc211.org/2005/resources/Codelist/gmxCodelists.xml#MD_KeywordTypeCode" codeListValue="place" codeSpace="ISOTC211/19115">place</MD_KeywordTypeCode>
          </type>
          <thesaurusName>
            <CI_Citation>
              <title>
                <gco:CharacterString>geonames</gco:CharacterString>
              </title>
              <date>
                <CI_Date>
                  <date>
                    <gco:Date>2012-11-01</gco:Date>
                  </date>
                  <dateType>
                    <CI_DateTypeCode codeList="http://www.isotc211.org/2005/resources/Codelist/gmxCodelists.xml#CI_DateTypeCode" codeListValue="creation" codeSpace="ISOTC211/19115">creation</CI_DateTypeCode>
                  </dateType>
                </CI_Date>
              </date>
              <identifier>
                <MD_Identifier>
                  <code>
                    <gco:CharacterString>http://www.geonames.org/ontology#</gco:CharacterString>
                  </code>
                </MD_Identifier>
              </identifier>
            </CI_Citation>
          </thesaurusName>
        </MD_Keywords>
      </descriptiveKeywords>
      <descriptiveKeywords>
        <MD_Keywords>
          <keyword>
            <gco:CharacterString>transportation</gco:CharacterString>
          </keyword>
          <keyword>
            <gco:CharacterString>Bikeways Existing Proposed</gco:CharacterString>
          </keyword>
          <type>
            <MD_KeywordTypeCode codeList="http://www.isotc211.org/2005/resources/Codelist/gmxCodelists.xml#MD_KeywordTypeCode" codeListValue="theme" codeSpace="ISOTC211/19115">theme</MD_KeywordTypeCode>
          </type>
          <thesaurusName>
            <CI_Citation>
              <title>
                <gco:CharacterString>lcsh</gco:CharacterString>
              </title>
              <date>
                <CI_Date>
                  <date>
                    <gco:Date>2011-04-26</gco:Date>
                  </date>
                  <dateType>
                    <CI_DateTypeCode codeList="http://www.isotc211.org/2005/resources/Codelist/gmxCodelists.xml#CI_DateTypeCode" codeListValue="creation" codeSpace="ISOTC211/19115">creation</CI_DateTypeCode>
                  </dateType>
                </CI_Date>
              </date>
              <date>
                <CI_Date>
                  <date>
                    <gco:Date>2011-04-26</gco:Date>
                  </date>
                  <dateType>
                    <CI_DateTypeCode codeList="http://www.isotc211.org/2005/resources/Codelist/gmxCodelists.xml#CI_DateTypeCode" codeListValue="revision" codeSpace="ISOTC211/19115">revision</CI_DateTypeCode>
                  </dateType>
                </CI_Date>
              </date>
              <identifier>
                <MD_Identifier>
                  <code>
                    <gco:CharacterString>http://id.loc.gov/authorities/subjects.html</gco:CharacterString>
                  </code>
                </MD_Identifier>
              </identifier>
            </CI_Citation>
          </thesaurusName>
        </MD_Keywords>
      </descriptiveKeywords>
      <descriptiveKeywords>
        <MD_Keywords>
          <keyword>
            <gco:CharacterString>Downloadable Data</gco:CharacterString>
          </keyword>
          <thesaurusName uuidref="723f6998-058e-11dc-8314-0800200c9a66" />
        </MD_Keywords>
      </descriptiveKeywords>
      <resourceConstraints>
        <MD_Constraints>
          <useLimitation>
            <gco:CharacterString>Disclaimer MarinMap/Marin County has attempted to verify the accuracy of the information contained in the following maps at the time of publication. Marin County assumes no liability for any errors, omissions, or inaccuracies in the information provided regardless of how caused. MarinMap/Marin County also assumes no liability for any decisions made or actions taken or not taken by the user of MarinMap/Marin County's Internet site in reliance upon any information or data furnished hereunder.THE MAPS PROVIDED BY MARIN COUNTY ARE PROVIDED ON AN “AS IS” AND AS AVAILABLE BASIS, WITHOUT WARRANTY OF ANY KIND, EXPRESS OR IMPLIED, INCLUDING, WITHOUT LIMITATION, ANY WARRANTIES OF MERCHANTABILITY, FITNESS FOR A PARTICULAR PURPOSE, NON-INFRINGEMENT OR OTHER WARRANTIES, CONDITIONS, GUARANTEES OR REPRESENTATIONS, WHETHER EXPRESS OR IMPLIED.THE MARIN COUNTY MAP SERVICES ARE COMPLEX AND MAY CONTAIN NONCONFORMITIES, DEFECTS OR ERRORS. MARIN COUNTY HEREBY DISCLAIMS ANY REPRESENTATION OR WARRANTY THAT THE MARIN COUNTY MAP SERVICES WILL MEET YOUR NEEDS, EXPECTATIONS OR INTENDED USE, THAT THE MARIN COUNTYMAP SERVICES WILL BE ERROR FREE OR UNINTERRUPTED, OR THAT NONCONFORMITIES CAN OR WILL BE CORRECTED. </gco:CharacterString>
          </useLimitation>
        </MD_Constraints>
      </resourceConstraints>
      <spatialRepresentationType>
        <MD_SpatialRepresentationTypeCode codeList="http://www.isotc211.org/2005/resources/Codelist/gmxCodelists.xml#MD_SpatialRepresentationTypeCode" codeListValue="vector" codeSpace="ISOTC211/19115">vector</MD_SpatialRepresentationTypeCode>
      </spatialRepresentationType>
      <language>
        <LanguageCode codeList="http://www.loc.gov/standards/iso639-2/php/code_list.php" codeListValue="eng" codeSpace="ISO639-2">eng</LanguageCode>
      </language>
      <characterSet>
        <MD_CharacterSetCode codeList="http://www.isotc211.org/2005/resources/Codelist/gmxCodelists.xml#MD_CharacterSetCode" codeListValue="utf8" codeSpace="ISOTC211/19115">utf8</MD_CharacterSetCode>
      </characterSet>
      <topicCategory>
        <MD_TopicCategoryCode>transportation</MD_TopicCategoryCode>
      </topicCategory>
      <environmentDescription>
        <gco:CharacterString>Microsoft Windows 7 Version 6.1 (Build 7601) Service Pack 1; Esri ArcGIS 10.5.1.7333</gco:CharacterString>
      </environmentDescription>
      <extent>
        <EX_Extent>
          <description>
            <gco:CharacterString>publication date</gco:CharacterString>
          </description>
          <temporalElement>
            <EX_TemporalExtent>
              <extent>
                <gml:TimePeriod gml:id="ID0EHNAE">
                  <gml:beginPosition>2014-10-01T00:00:00</gml:beginPosition>
                  <gml:endPosition indeterminatePosition="unknown" />
                </gml:TimePeriod>
              </extent>
            </EX_TemporalExtent>
          </temporalElement>
        </EX_Extent>
      </extent>
      <extent>
        <EX_Extent>
          <geographicElement>
            <EX_GeographicBoundingBox>
              <extentTypeCode>
                <gco:Boolean>true</gco:Boolean>
              </extentTypeCode>
              <westBoundLongitude>
                <gco:Decimal>-122.839783</gco:Decimal>
              </westBoundLongitude>
              <eastBoundLongitude>
                <gco:Decimal>-122.406402</gco:Decimal>
              </eastBoundLongitude>
              <southBoundLatitude>
                <gco:Decimal>37.802318</gco:Decimal>
              </southBoundLatitude>
              <northBoundLatitude>
                <gco:Decimal>38.194766</gco:Decimal>
              </northBoundLatitude>
            </EX_GeographicBoundingBox>
          </geographicElement>
        </EX_Extent>
      </extent>
    </MD_DataIdentification>
  </identificationInfo>
  <distributionInfo>
    <MD_Distribution>
      <distributionFormat>
        <MD_Format>
          <name>
            <gco:CharacterString>Shapefile</gco:CharacterString>
          </name>
          <version>
            <gco:CharacterString>ArcGIS 10.2</gco:CharacterString>
          </version>
        </MD_Format>
      </distributionFormat>
      <distributor>
        <MD_Distributor>
          <distributorContact>
            <CI_ResponsibleParty>
              <organisationName>
                <gco:CharacterString>UC Berkeley Library </gco:CharacterString>
              </organisationName>
              <positionName>
                <gco:CharacterString>GIS Librarian </gco:CharacterString>
              </positionName>
              <contactInfo>
                <CI_Contact>
                  <phone>
                    <CI_Telephone>
                      <voice>
                        <gco:CharacterString>(510) 642-2997</gco:CharacterString>
                      </voice>
                    </CI_Telephone>
                  </phone>
                  <address>
                    <CI_Address>
                      <deliveryPoint>
                        <gco:CharacterString>50 McCone Hall</gco:CharacterString>
                      </deliveryPoint>
                      <city>
                        <gco:CharacterString>Berkeley</gco:CharacterString>
                      </city>
                      <administrativeArea>
                        <gco:CharacterString>CA</gco:CharacterString>
                      </administrativeArea>
                      <postalCode>
                        <gco:CharacterString>94720</gco:CharacterString>
                      </postalCode>
                      <country>
                        <Country codeList="http://www.iso.org/iso/country_codes/iso_3166_code_lists.htm" codeListValue="US" codeSpace="ISO3166-1">US</Country>
                      </country>
                      <electronicMailAddress>
                        <gco:CharacterString>eart@library.berkeley.edu</gco:CharacterString>
                      </electronicMailAddress>
                    </CI_Address>
                  </address>
                </CI_Contact>
              </contactInfo>
              <role>
                <CI_RoleCode codeList="http://www.isotc211.org/2005/resources/Codelist/gmxCodelists.xml#CI_RoleCode" codeListValue="distributor" codeSpace="ISOTC211/19115">distributor</CI_RoleCode>
              </role>
            </CI_ResponsibleParty>
          </distributorContact>
        </MD_Distributor>
      </distributor>
      <transferOptions>
        <MD_DigitalTransferOptions>
          <transferSize>
            <gco:Real>0.433</gco:Real>
          </transferSize>
        </MD_DigitalTransferOptions>
      </transferOptions>
    </MD_Distribution>
  </distributionInfo>
  <dataQualityInfo>
    <DQ_DataQuality>
      <scope>
        <DQ_Scope>
          <level>
            <MD_ScopeCode codeList="http://www.isotc211.org/2005/resources/Codelist/gmxCodelists.xml#MD_ScopeCode" codeListValue="dataset" codeSpace="ISOTC211/19115">dataset</MD_ScopeCode>
          </level>
        </DQ_Scope>
      </scope>
      <lineage>
        <LI_Lineage>
          <statement>
            <gco:CharacterString>Data downloaded from http://www.marinmap.org/DNN/Data/GISDataDownLoad.aspx on October 8, 2014</gco:CharacterString>
          </statement>
          <processStep>
            <LI_ProcessStep>
              <description>
                <gco:CharacterString>Changed "bikeway.shp" to "marin_bikeways_2014.shp"</gco:CharacterString>
              </description>
              <rationale>
                <gco:CharacterString>Date acquired from geoprocessing history </gco:CharacterString>
              </rationale>
              <dateTime>
                <gco:DateTime>2015-04-06T00:00:00</gco:DateTime>
              </dateTime>
              <processor>
                <CI_ResponsibleParty>
                  <organisationName>
                    <gco:CharacterString>UC Berkeley Library </gco:CharacterString>
                  </organisationName>
                  <positionName>
                    <gco:CharacterString>GIS Librarian </gco:CharacterString>
                  </positionName>
                  <contactInfo>
                    <CI_Contact>
                      <phone>
                        <CI_Telephone>
                          <voice>
                            <gco:CharacterString>(510) 642-2997</gco:CharacterString>
                          </voice>
                        </CI_Telephone>
                      </phone>
                      <address>
                        <CI_Address>
                          <deliveryPoint>
                            <gco:CharacterString>50 McCone Hall</gco:CharacterString>
                          </deliveryPoint>
                          <city>
                            <gco:CharacterString>Berkeley</gco:CharacterString>
                          </city>
                          <administrativeArea>
                            <gco:CharacterString>CA</gco:CharacterString>
                          </administrativeArea>
                          <postalCode>
                            <gco:CharacterString>94720</gco:CharacterString>
                          </postalCode>
                          <country>
                            <Country codeList="http://www.iso.org/iso/country_codes/iso_3166_code_lists.htm" codeListValue="US" codeSpace="ISO3166-1">US</Country>
                          </country>
                          <electronicMailAddress>
                            <gco:CharacterString>eart@library.berkeley.edu</gco:CharacterString>
                          </electronicMailAddress>
                        </CI_Address>
                      </address>
                    </CI_Contact>
                  </contactInfo>
                  <role>
                    <CI_RoleCode codeList="http://www.isotc211.org/2005/resources/Codelist/gmxCodelists.xml#CI_RoleCode" codeListValue="pointOfContact" codeSpace="ISOTC211/19115">pointOfContact</CI_RoleCode>
                  </role>
                </CI_ResponsibleParty>
              </processor>
            </LI_ProcessStep>
          </processStep>
        </LI_Lineage>
      </lineage>
    </DQ_DataQuality>
  </dataQualityInfo>
  <metadataMaintenance>
    <MD_MaintenanceInformation>
      <maintenanceAndUpdateFrequency>
        <MD_MaintenanceFrequencyCode codeList="http://www.isotc211.org/2005/resources/Codelist/gmxCodelists.xml#MD_MaintenanceFrequencyCode" codeListValue="asNeeded" codeSpace="ISOTC211/19115">asNeeded</MD_MaintenanceFrequencyCode>
      </maintenanceAndUpdateFrequency>
    </MD_MaintenanceInformation>
  </metadataMaintenance>
</MD_Metadata>