[{"geoblacklight_version": "1.0", "dc_description_s": "This dataset contains the Sonoma County school district boundaries.  There are 40 districts in Sonoma County that range in enrollment from 12 students to over 12,000 students.  These district boundaries indicate the jurisdiction each district covers within the county.", "layer_geom_type_s": "Polygon", "layer_modified_dt": "2012-11-28T23:34:19.003Z", "dc_creator_sm": "County of Sonoma ISD GIS Central", "layer_id_s": "s76022", "dct_references_s": "{\"http://www.opengis.net/def/serviceType/ogc/wfs\":\"https://geoservices.lib.berkeley.edu/geoserver/wfs\",\"http://www.opengis.net/def/serviceType/ogc/wms\":\"https://geoservices.lib.berkeley.edu/geoserver/wms\",\"http://schema.org/downloadUrl\":\"http://spatial.lib.berkeley.edu/public/ark28722-s76022/data.zip\"}", "dc_identifier_s": "http://spatial.lib.berkeley.edu/viewpublic/ark28722-s76022", "dct_provenance_s": "Berkeley", "dc_title_s": "SCGISDB2_BASE_ADM_SCHOOLDISTRICTS", "layer_slug_s": "ark28722-s76022", "dc_publisher_s": "Santa Rosa (Calif.). County Of Sonoma Gis Central.", "dc_format_s": "Shapefile", "dc_subject_sm": ["Education", "Schools", "Boundaries"], "solr_year_i": 2003, "solr_geom": "ENVELOPE(-123.634515, -122.347454, 38.856934, 38.062416)", "dc_rights_s": "Public", "dct_spatial_sm": ["Sonoma County (Calif.)"]}]