[
    {
        "dc_creator_sm":"MarinMap",
        "dc_description_s":"Ripples of the ocean, bay and water bodies (lakes and lagoon, etc) shorelines",
        "dc_format_s":"Shapefile",
        "dc_identifier_s":"http://spatial.lib.berkeley.edu/viewpublic/ark28722-s7r309",
        "dc_publisher_s":"San Rafael (Calif.). County Of Marin.",
        "dc_rights_s":"Public",
        "dc_subject_sm":[
            "Ocean",
            "Estuaries"
        ],
        "dc_title_s":"Water Ripple Marin County 2007",
        "dct_provenance_s":"Berkeley",
        "dct_references_s":"{\"http://www.opengis.net/def/serviceType/ogc/wfs\":\"https://geoservices.lib.berkeley.edu/geoserver/wfs\",\"http://www.opengis.net/def/serviceType/ogc/wms\":\"https://geoservices.lib.berkeley.edu/geoserver/wms\",\"http://schema.org/downloadUrl\":\"https://spatial.lib.berkeley.edu/public/ark28722-s7r309/data.zip\"}",
        "dct_spatial_sm":[
            "Marin County (Calif.)"
        ],
        "geoblacklight_version":"1.0",
        "layer_geom_type_s":"Line",
        "layer_id_s":"s7r309",
        "layer_modified_dt":"2013-10-23T21:37:43.737Z",
        "layer_slug_s":"ark28722-s7r309",
        "solr_geom":"ENVELOPE(-123.037683, -122.383908, 38.327922, 37.794819)",
        "solr_year_i":2011
    }
]
