{
  "dct_creator_sm": [
    "County of Napa ITS Department"
  ],
  "dct_description_sm": [
    "Location of addresses considered to be sub-addresses of a main address."
  ],
  "dct_format_s": "Shapefile",
  "dct_identifier_sm": [
    "https://spatial.lib.berkeley.edu/viewpublic/ark28722-s7tc7b"
  ],
  "dct_publisher_sm": [
    "Napa County (Calif.). County Of Napa."
  ],
  "dct_accessRights_s": "Public",
  "dct_subject_sm": [
    "Structure"
  ],
  "dct_title_s": "SubAddressPoint",
  "schema_provider_s": "University of California Berkeley",
  "dct_references_s": "{\"http://www.opengis.net/def/serviceType/ogc/wfs\":\"https://geoservices.lib.berkeley.edu/geoserver/wfs\",\"http://www.opengis.net/def/serviceType/ogc/wms\":\"https://geoservices.lib.berkeley.edu/geoserver/wms\",\"http://schema.org/downloadUrl\":\"https://spatial.lib.berkeley.edu/public/ark28722-s7tc7b/data.zip\"}",
  "dct_spatial_sm": [
    "Napa County (Calif.)"
  ],
  "dct_temporal_sm": [
    "2007"
  ],
  "gbl_resourceType_sm": [
    "Point data",
    "Vector data"
  ],
  "gbl_wxsIdentifier_s": "s7tc7b",
  "gbl_mdModified_dt": "2012-11-28T23:35:01.258Z",
  "id": "ark28722-s7tc7b",
  "locn_geometry": "ENVELOPE(-122.600753, -122.23886, 38.59186, 38.154031)",
  "dcat_bbox": "ENVELOPE(-122.600753, -122.23886, 38.59186, 38.154031)",
  "gbl_indexYear_im": [
    2007
  ],
  "gbl_mdVersion_s": "Aardvark",
  "gbl_resourceClass_sm": [
    "Datasets"
  ]
}