[
    {
        "dc_creator_sm":"Department of Telecommunications and Information Services",
        "dc_description_s":"US Census 2000 Block Group Geography modified to conform with SFGIS Library Geography (Streets, Lakes, et al.). Water areas have been clipped from this layer.",
        "dc_format_s":"Shapefile",
        "dc_identifier_s":"http://spatial.lib.berkeley.edu/viewpublic/ark28722-s70s3h",
        "dc_publisher_s":"San Francisco (Calif.). Department Of Telecommunications and Information Services.",
        "dc_rights_s":"Public",
        "dc_subject_sm":[
            "Census Block Groups",
            "Demographics"
        ],
        "dc_title_s":"US CENSUS 2000 Block Groups (No Water)",
        "dct_provenance_s":"Berkeley",
        "dct_references_s":"{\"http://www.opengis.net/def/serviceType/ogc/wfs\":\"https://geoservices.lib.berkeley.edu/geoserver/wfs\",\"http://www.opengis.net/def/serviceType/ogc/wms\":\"https://geoservices.lib.berkeley.edu/geoserver/wms\",\"http://schema.org/downloadUrl\":\"https://spatial.lib.berkeley.edu/public/ark28722-s70s3h/data.zip\"}",
        "dct_spatial_sm":[
            "San Francisco County (Calif.)",
            "San Francisco (Calif.)"
        ],
        "geoblacklight_version":"1.0",
        "layer_geom_type_s":"Polygon",
        "layer_id_s":"s70s3h",
        "layer_modified_dt":"2012-11-28T23:34:29.777Z",
        "layer_slug_s":"ark28722-s70s3h",
        "solr_geom":"ENVELOPE(-123.110826, -122.32583, 37.864866, 37.69087)",
        "solr_year_i":2003
    }
]