{
  "dct_creator_sm": [
    "Humboldt County Community Development Services"
  ],
  "dct_description_sm": [
    "Humboldt County Fire District Boundaries and Response Areas"
  ],
  "dct_format_s": "Shapefile",
  "dct_identifier_sm": [
    "https://spatial.lib.berkeley.edu/viewpublic/berkeley-s7rt0j"
  ],
  "dct_accessRights_s": "Public",
  "dct_subject_sm": [
    "Boundaries",
    "Fire Protection Districts",
    "Administrative and Political Divisions"
  ],
  "dct_title_s": "Fire Districts, Humboldt County, California, 2013",
  "dct_issued_s": "2013-04-16",
  "schema_provider_s": "University of California Berkeley",
  "dct_references_s": "{\"http://www.opengis.net/def/serviceType/ogc/wfs\":\"https://geoservices.lib.berkeley.edu/geoserver/wfs\",\"http://www.opengis.net/def/serviceType/ogc/wms\":\"https://geoservices.lib.berkeley.edu/geoserver/wms\",\"http://www.isotc211.org/schemas/2005/gmd/\":\"https://spatial.lib.berkeley.edu/metadata/berkeley-s7rt0j/iso19139.xml\",\"http://schema.org/downloadUrl\":\"https://spatial.lib.berkeley.edu/public/berkeley-s7rt0j/data.zip\"}",
  "dct_spatial_sm": [
    "Humboldt County (Calif.)"
  ],
  "gbl_resourceType_sm": [
    "Polygon data",
    "Vector data"
  ],
  "gbl_wxsIdentifier_s": "s7rt0j",
  "gbl_mdModified_dt": "2018-02-23T23:34:35.206Z",
  "id": "berkeley-s7rt0j",
  "locn_geometry": "ENVELOPE(-124.442868, -123.436998, 41.473523, 39.918094)",
  "dcat_bbox": "ENVELOPE(-124.442868, -123.436998, 41.473523, 39.918094)",
  "gbl_indexYear_im": [
    2013
  ],
  "gbl_mdVersion_s": "Aardvark",
  "gbl_resourceClass_sm": [
    "Datasets"
  ]
}